phosphomatics/__init__.py
phosphomatics/phosphomatics.py
phosphomatics_api_wrapper-0.0.1.dist-info/LICENSE
phosphomatics_api_wrapper-0.0.1.dist-info/METADATA
phosphomatics_api_wrapper-0.0.1.dist-info/WHEEL
phosphomatics_api_wrapper-0.0.1.dist-info/top_level.txt
phosphomatics_api_wrapper-0.0.1.dist-info/RECORD
