Metadata-Version: 2.1
Name: phosphomatics-api-wrapper
Version: 0.0.1
Summary: A python wrapper for the phosphomatics API
Home-page: https://github.com/mgleeming/phosphomatics-api-wrapper.git
Author: Michael Leeming
Author-email: leemingm@unimelb.edu.au
License: BSD
Platform: UNKNOWN
Classifier: License :: OSI Approved :: BSD License
Classifier: Programming Language :: Python :: 3
Classifier: Programming Language :: Python :: 3.7
Requires-Dist: requests
